pymallet
