Metadata-Version: 1.0
Name: pymallet
Version: 0.1.1
Summary: Mallet (natural language processing) wrapper in Python
Home-page: UNKNOWN
Author: Team DSSG
Author-email: nathanleiby@gmail.com
License: MIT
Platform: UNKNOWN
